babelwidget/__init__.py
babelwidget/version.py
babelwidget/api/backend.py
babelwidget/api/dialog.py
babelwidget/api/layout.py
babelwidget/api/widget.py
babelwidget/catalog/_generic/path_chooser.py
babelwidget/catalog/_pyqt/color.py
babelwidget/catalog/_pyqt/event.py
babelwidget/catalog/_pyqt/dialog/message.py
babelwidget/catalog/_pyqt/layout/scroll_container.py
babelwidget/catalog/_pyqt/widget/button.py
babelwidget/catalog/_pyqt/widget/dropdown_choices.py
babelwidget/catalog/_pyqt/widget/image.py
babelwidget/catalog/_pyqt/widget/label.py
babelwidget/catalog/_pyqt/widget/menu.py
babelwidget/catalog/_pyqt/widget/radio_choices.py
babelwidget/catalog/_pyqt/widget/text_box.py
babelwidget/catalog/_pyqt/widget/text_line.py
babelwidget/catalog/pyqt6/_image.py
babelwidget/catalog/pyqt6/color.py
babelwidget/catalog/pyqt6/constant.py
babelwidget/catalog/pyqt6/dialog.py
babelwidget/catalog/pyqt6/event.py
babelwidget/catalog/pyqt6/message.py
babelwidget/catalog/pyqt6/widget.py
babelwidget/constant/definition.py
babelwidget/constant/path.py
babelwidget/extension/python.py
babelwidget/task/building.py
babelwidget/task/importing.py
babelwidget/type/backend/main.py
babelwidget/type/backend/protocol.py
babelwidget/type/dialog/generic.py
babelwidget/type/dialog/message.py
babelwidget/type/layout/scroll_container.py
babelwidget/type/widget/button.py
babelwidget/type/widget/dropdown_choice.py
babelwidget/type/widget/image.py
babelwidget/type/widget/label.py
babelwidget/type/widget/menu.py
babelwidget/type/widget/radio_choice.py
babelwidget/type/widget/text_box.py
babelwidget/type/widget/text_line.py
babelwidget/type/widget/text_list.py
babelwidget-2025.4.dist-info/METADATA
babelwidget-2025.4.dist-info/WHEEL
babelwidget-2025.4.dist-info/top_level.txt
babelwidget-2025.4.dist-info/RECORD
