Metadata-Version: 2.4
Name: babelwidget
Version: 2025.4
Summary: A Meta Widget Library That Speaks Several Backends
Home-page: https://src.koda.cnrs.fr/eric.debreuve/babelwidget/
Author: Eric Debreuve
Author-email: eric.debreuve@cnrs.fr
License: CeCILL-2.1
Project-URL: Documentation, https://src.koda.cnrs.fr/eric.debreuve/babelwidget/-/wikis/home
Project-URL: Source, https://src.koda.cnrs.fr/eric.debreuve/babelwidget/
Keywords: app,application,development,graphical interface
Classifier: Topic :: Software Development
Classifier: Intended Audience :: Science/Research
Classifier: License :: OSI Approved :: CEA CNRS Inria Logiciel Libre License, version 2.1 (CeCILL-2.1)
Classifier: Programming Language :: Python :: 3
Classifier: Development Status :: 4 - Beta
Requires-Python: >=3.11
Dynamic: author
Dynamic: author-email
Dynamic: classifier
Dynamic: description
Dynamic: description-content-type
Dynamic: home-page
Dynamic: keywords
Dynamic: license
Dynamic: project-url
Dynamic: requires-python
Dynamic: summary
